tool_package/__init__.py
tool_package/add.py
tool_package/email_util.py
tool_package/subtract.py
tools_package-0.1.4.dist-info/LICENSE
tools_package-0.1.4.dist-info/METADATA
tools_package-0.1.4.dist-info/WHEEL
tools_package-0.1.4.dist-info/top_level.txt
tools_package-0.1.4.dist-info/RECORD
